doculinkr/__init__.py
doculinkr/cli.py
doculinkr/utils.py
doculinkr/templates/blog_docusaurus_config.js.j2
doculinkr/templates/default_index.js.j2
doculinkr/templates/doculinkr.yaml.j2
doculinkr/templates/example_getting_started.md.j2
doculinkr/templates/example_index.md.j2
doculinkr/templates/homepageFeatures.js.j2
doculinkr/templates/no_blog_docusaurus_config.js.j2
doculinkr/templates/sidebars.js.j2
doculinkr/templates/symlink-docs-plugin.js.j2
doculinkr-0.1.0.dist-info/LICENSE
doculinkr-0.1.0.dist-info/METADATA
doculinkr-0.1.0.dist-info/WHEEL
doculinkr-0.1.0.dist-info/entry_points.txt
doculinkr-0.1.0.dist-info/top_level.txt
doculinkr-0.1.0.dist-info/RECORD
