Metadata-Version: 2.1
Name: doculinkr
Version: 0.1.0
Summary: A Python CLI to seamlessly link & manage Docusaurus documentation from multiple Git projects into one unified website.
Home-page: https://github.com/FormuLearn/DocuLinkr
Author: Nicholas Roy / FormuLearn B.V.
Author-email: nicholas.roy@formulearn.org
Classifier: Programming Language :: Python :: 3
Classifier: License :: OSI Approved :: MIT License
Classifier: Operating System :: OS Independent
Classifier: Environment :: Console
Classifier: Intended Audience :: Developers
Classifier: Topic :: Documentation
Classifier: Topic :: Software Development :: Build Tools
Requires-Python: >=3.10
License-File: LICENSE
Requires-Dist: GitPython ==3.1.44
Requires-Dist: Jinja2 ==3.1.6
Requires-Dist: MarkupSafe ==3.0.2
Requires-Dist: PyYAML ==6.0.2
Requires-Dist: Pygments ==2.19.1
Requires-Dist: SecretStorage ==3.3.3
Requires-Dist: build ==1.2.2.post1
Requires-Dist: certifi ==2025.4.26
Requires-Dist: cffi ==1.17.1
Requires-Dist: charset-normalizer ==3.4.2
Requires-Dist: click ==8.2.1
Requires-Dist: cryptography ==45.0.3
Requires-Dist: docutils ==0.21.2
Requires-Dist: gitdb ==4.0.12
Requires-Dist: id ==1.5.0
Requires-Dist: idna ==3.10
Requires-Dist: jaraco.classes ==3.4.0
Requires-Dist: jaraco.context ==6.0.1
Requires-Dist: jaraco.functools ==4.1.0
Requires-Dist: jeepney ==0.9.0
Requires-Dist: keyring ==25.6.0
Requires-Dist: markdown-it-py ==3.0.0
Requires-Dist: mdurl ==0.1.2
Requires-Dist: more-itertools ==10.7.0
Requires-Dist: nh3 ==0.2.21
Requires-Dist: packaging ==25.0
Requires-Dist: pycparser ==2.22
Requires-Dist: pyproject-hooks ==1.2.0
Requires-Dist: readme-renderer ==44.0
Requires-Dist: requests-toolbelt ==1.0.0
Requires-Dist: requests ==2.32.3
Requires-Dist: rfc3986 ==2.0.0
Requires-Dist: rich ==14.0.0
Requires-Dist: setuptools ==80.9.0
Requires-Dist: smmap ==5.0.2
Requires-Dist: twine ==6.1.0
Requires-Dist: urllib3 ==2.4.0
